a2d/__init__.py
a2d/main.py
a2d/utils.py
a2d-0.0.1.dist-info/METADATA
a2d-0.0.1.dist-info/WHEEL
a2d-0.0.1.dist-info/entry_points.txt
a2d-0.0.1.dist-info/top_level.txt
a2d-0.0.1.dist-info/RECORD
