Metadata-Version: 2.1
Name: a2d
Version: 0.0.1
Summary: Archive 4Chan threads to Discord
Home-page: https://github.com/scrazzz/a2d
Author: scrazzz
License: MIT
Requires-Python: >=3.8.0
Requires-Dist: requests (>=2.28.1)
Requires-Dist: click (>=8.1.3)
Requires-Dist: rich (>=13.3.2)
Requires-Dist: discord.py (>=2.1.0)
